FDSMLP/Simplex.py
FDSMLP/__init__.py
FDSMLP/core/BasicSimplex.py
FDSMLP/core/SimplexError.py
FDSMLP/core/__init__.py
FDSMLP/core/utils/InitializationError.py
FDSMLP/core/utils/Normailze_simplex.py
FDSMLP/core/utils/Two_step_simplex_init.py
FDSMLP/core/utils/__init__.py
FDSMLP/core/utils/input_parser.py
FDSMLP/core/utils/matrix.py
FDSMLP-1.0.3.dist-info/LICENSE
FDSMLP-1.0.3.dist-info/METADATA
FDSMLP-1.0.3.dist-info/WHEEL
FDSMLP-1.0.3.dist-info/top_level.txt
FDSMLP-1.0.3.dist-info/RECORD
