Metadata-Version: 2.1
Name: FDSMLP
Version: 1.0.3
Summary: 可以打印单纯形表的LP求解器！
Home-page: https://github.com/xuanfengzu/FDSMLP
Author: Micheal
Classifier: Programming Language :: Python :: 3
Classifier: License :: OSI Approved :: BSD License
Classifier: Operating System :: OS Independent
License-File: LICENSE
